mt/pandas/__init__.py
mt/pandas/convert.py
mt/pandas/csv.py
mt/pandas/custom_accessors.py
mt/pandas/dataclass.py
mt/pandas/dataframe.py
mt/pandas/dataframe_processing.py
mt/pandas/dftype.py
mt/pandas/json.py
mt/pandas/ndarray.py
mt/pandas/pdh5.py
mt/pandas/series.py
mt/pandas/version.py
mt/pandas/word.py
mt/pd/__init__.py
mtpandas-1.17.17.data/scripts/dfconvert
mtpandas-1.17.17.data/scripts/dfview
mtpandas-1.17.17.dist-info/licenses/LICENSE
mtpandas-1.17.17.dist-info/METADATA
mtpandas-1.17.17.dist-info/WHEEL
mtpandas-1.17.17.dist-info/top_level.txt
mtpandas-1.17.17.dist-info/RECORD
