Metadata-Version: 2.4
Name: mtpandas
Version: 1.17.17
Summary: MT's extra modules for pandas.
Home-page: https://github.com/inteplus/mtpandas
Author: ['Minh-Tri Pham']
License: MIT
Project-URL: Documentation, https://mtdoc.readthedocs.io/en/latest/mt.pandas/mt.pandas.html
Project-URL: Source Code, https://github.com/inteplus/mtpandas
Requires-Python: >=3.6
License-File: LICENSE
Requires-Dist: pandas>=1.5
Requires-Dist: pandas_parallel_apply
Requires-Dist: pathos
Requires-Dist: mtbase>=4.32.32
Requires-Dist: mtopencv>=1.11.2
Requires-Dist: tqdm
Requires-Dist: tabview
Dynamic: author
Dynamic: home-page
Dynamic: license
Dynamic: license-file
Dynamic: project-url
Dynamic: requires-dist
Dynamic: requires-python
Dynamic: summary
